CHANGES.txt
LICENSE.txt
MANIFEST.in
README.rst
setup.py
pyramid_mako_starters/__init__.py
pyramid_mako_starters.egg-info/PKG-INFO
pyramid_mako_starters.egg-info/SOURCES.txt
pyramid_mako_starters.egg-info/dependency_links.txt
pyramid_mako_starters.egg-info/entry_points.txt
pyramid_mako_starters.egg-info/requires.txt
pyramid_mako_starters.egg-info/top_level.txt
pyramid_mako_starters/scaffolds/__init__.py
pyramid_mako_starters/scaffolds/tests.py
pyramid_mako_starters/scaffolds/alchemy_mako/CHANGES.txt_tmpl
pyramid_mako_starters/scaffolds/alchemy_mako/MANIFEST.in_tmpl
pyramid_mako_starters/scaffolds/alchemy_mako/README.txt_tmpl
pyramid_mako_starters/scaffolds/alchemy_mako/development.ini_tmpl
pyramid_mako_starters/scaffolds/alchemy_mako/production.ini_tmpl
pyramid_mako_starters/scaffolds/alchemy_mako/setup.py_tmpl
pyramid_mako_starters/scaffolds/alchemy_mako/+package+/__init__.py
pyramid_mako_starters/scaffolds/alchemy_mako/+package+/models.py
pyramid_mako_starters/scaffolds/alchemy_mako/+package+/tests.py_tmpl
pyramid_mako_starters/scaffolds/alchemy_mako/+package+/views.py_tmpl
pyramid_mako_starters/scaffolds/alchemy_mako/+package+/scripts/__init__.py
pyramid_mako_starters/scaffolds/alchemy_mako/+package+/scripts/initializedb.py
pyramid_mako_starters/scaffolds/alchemy_mako/+package+/static/pyramid-16x16.png
pyramid_mako_starters/scaffolds/alchemy_mako/+package+/static/pyramid.png
pyramid_mako_starters/scaffolds/alchemy_mako/+package+/static/theme.css
pyramid_mako_starters/scaffolds/alchemy_mako/+package+/static/theme.min.css
pyramid_mako_starters/scaffolds/alchemy_mako/+package+/templates/mytemplate.mako_tmpl
pyramid_mako_starters/scaffolds/starter_mako/CHANGES.txt_tmpl
pyramid_mako_starters/scaffolds/starter_mako/MANIFEST.in_tmpl
pyramid_mako_starters/scaffolds/starter_mako/README.txt_tmpl
pyramid_mako_starters/scaffolds/starter_mako/development.ini_tmpl
pyramid_mako_starters/scaffolds/starter_mako/production.ini_tmpl
pyramid_mako_starters/scaffolds/starter_mako/setup.py_tmpl
pyramid_mako_starters/scaffolds/starter_mako/+package+/__init__.py
pyramid_mako_starters/scaffolds/starter_mako/+package+/tests.py_tmpl
pyramid_mako_starters/scaffolds/starter_mako/+package+/views.py_tmpl
