Metadata-Version: 1.1
Name: pyramid-mako-starters
Version: 0.1.2
Summary: Pyramid project scaffolds using Mako templates
Home-page: https://github.com/ronnix/pyramid-mako-starters
Author: Ronan Amicel
Author-email: ronan.amicel@gmail.com
License: BSD
Platform: UNKNOWN
Classifier: Framework :: Pyramid
Classifier: Intended Audience :: Developers
Classifier: License :: OSI Approved :: BSD License
Classifier: Programming Language :: Python
Classifier: Topic :: Internet :: WWW/HTTP
Classifier: Topic :: Internet :: WWW/HTTP :: WSGI
